sdss_module/__init__.py
sdss_module/add.py
sdss_module/divide.py
sdss_module/multiply.py
sdss_module/subtract.py
sdss_module-0.0.1.dist-info/METADATA
sdss_module-0.0.1.dist-info/WHEEL
sdss_module-0.0.1.dist-info/top_level.txt
sdss_module-0.0.1.dist-info/RECORD
