Metadata-Version: 2.1
Name: sdss-module
Version: 0.0.1
Summary: My first Python package
Home-page: UNKNOWN
Author: Shaunak Dhande
Author-email: shaunak.dhande@innoplexus.com
License: UNKNOWN
Keywords: python,first package
Platform: UNKNOWN
Classifier: Programming Language :: Python :: 3
Classifier: License :: OSI Approved :: MIT License
Classifier: Operating System :: OS Independent
